{
    "name": "Plant 2",
    "authorId": "6GDRYduquMP",
    "authorName": "Urban Plants",
    "createTime": "2021-06-06T15:29:46.434184Z",
    "updateTime": "2021-06-06T15:36:26.623171Z",
    "license": "CREATIVE_COMMONS_BY",
    "visibility": "PUBLIC",
    "tags": [],
    "likes": 0,
    "formats": [
        {
            "root": {
                "relativePath": "Plants vase N251220/Plants vase N251220.obj",
                "contentType": "text/plain"
            },
            "resources": [
                {
                    "relativePath": "Plants vase N251220/Plants vase N251220.mtl",
                    "contentType": "text/plain"
                },
                {
                    "relativePath": "Plants vase N251220/D:/New folder 2/14-5ston.jpg",
                    "contentType": "image/jpeg"
                },
                {
                    "relativePath": "Plants vase N251220/D:/New folder 2/archmode.jpg",
                    "contentType": "image/jpeg"
                },
                {
                    "relativePath": "Plants vase N251220/D:/New folder 2/depositp.jpg",
                    "contentType": "image/jpeg"
                },
                {
                    "relativePath": "Plants vase N251220/D:/New folder 2/leaves_t.jpg",
                    "contentType": "image/jpeg"
                },
                {
                    "relativePath": "Plants vase N251220/D:/New folder 2/SoilCrac.jpg",
                    "contentType": "image/jpeg"
                },
                {
                    "relativePath": "Plants vase N251220/D:/New folder 2/textile/Suede 2000 x 2000 px 210820 sml.jpg",
                    "contentType": "image/jpeg"
                }
            ],
            "formatComplexity": {
                "triangleCount": "35564"
            },
            "formatType": "OBJ"
        },
        {
            "root": {
                "relativePath": "Plants vase N251220.gltf",
                "contentType": "model/gltf+json"
            },
            "resources": [
                {
                    "relativePath": "Plants vase N251220.bin",
                    "contentType": "application/octet-stream"
                },
                {
                    "relativePath": "Plants vase N251220/D:/New folder 2/archmode.jpg",
                    "contentType": "image/jpeg"
                },
                {
                    "relativePath": "Plants vase N251220/D:/New folder 2/textile/Suede 2000 x 2000 px 210820 sml.jpg",
                    "contentType": "image/jpeg"
                },
                {
                    "relativePath": "Plants vase N251220/D:/New folder 2/leaves_t.jpg",
                    "contentType": "image/jpeg"
                },
                {
                    "relativePath": "Plants vase N251220/D:/New folder 2/depositp.jpg",
                    "contentType": "image/jpeg"
                },
                {
                    "relativePath": "Plants vase N251220/D:/New folder 2/14-5ston.jpg",
                    "contentType": "image/jpeg"
                },
                {
                    "relativePath": "Plants vase N251220/D:/New folder 2/SoilCrac.jpg",
                    "contentType": "image/jpeg"
                }
            ],
            "formatComplexity": {
                "triangleCount": "35564"
            },
            "formatType": "GLTF2"
        }
    ],
    "presentationParams": {
        "orientingRotation": {
            "w": 1
        },
        "colorSpace": "LINEAR",
        "backgroundColor": "#eeeeee"
    }
}