{
    "name": "Phone Block",
    "authorId": "0UqAaUibpZX",
    "authorName": "James Tichenor",
    "createTime": "2018-03-19T21:18:57.531649Z",
    "updateTime": "2020-06-25T10:10:53.918770Z",
    "license": "CREATIVE_COMMONS_BY",
    "visibility": "PUBLIC",
    "tags": [],
    "likes": 0,
    "formats": [
        {
            "root": {
                "relativePath": "model.gltf",
                "contentType": "model/gltf+json"
            },
            "resources": [
                {
                    "relativePath": "model.bin",
                    "contentType": "application/octet-stream"
                }
            ],
            "formatComplexity": {
                "triangleCount": "212"
            },
            "formatType": "GLTF2"
        },
        {
            "root": {
                "relativePath": "model.gltf",
                "contentType": "model/gltf+json"
            },
            "resources": [
                {
                    "relativePath": "model.bin",
                    "contentType": "application/octet-stream"
                }
            ],
            "formatComplexity": {
                "triangleCount": "212"
            },
            "formatType": "GLTF"
        },
        {
            "root": {
                "relativePath": "model.fbx",
                "contentType": "application/octet-stream"
            },
            "formatComplexity": {},
            "formatType": "FBX"
        },
        {
            "root": {
                "relativePath": "model.obj",
                "contentType": "text/plain"
            },
            "resources": [
                {
                    "relativePath": "materials.mtl",
                    "contentType": "text/plain"
                }
            ],
            "formatComplexity": {
                "triangleCount": "76"
            },
            "formatType": "OBJ"
        }
    ],
    "presentationParams": {
        "orientingRotation": {
            "w": 1
        },
        "colorSpace": "LINEAR",
        "backgroundColor": "#000000"
    }
}