{
    "name": "Another box",
    "description": "Sirkut",
    "authorId": "fOtdRVf7-r1",
    "authorName": "Bill Baran (Sirkut)",
    "createTime": "2018-08-18T22:56:35.874508Z",
    "updateTime": "2021-06-10T04:52:19.995210Z",
    "license": "CREATIVE_COMMONS_BY",
    "visibility": "PUBLIC",
    "tags": [
        "scenes"
    ],
    "likes": 0,
    "formats": [
        {
            "root": {
                "relativePath": "box2.obj",
                "contentType": "text/plain"
            },
            "resources": [
                {
                    "relativePath": "box2.mtl",
                    "contentType": "text/plain"
                }
            ],
            "formatComplexity": {
                "triangleCount": "360"
            },
            "formatType": "OBJ"
        },
        {
            "root": {
                "relativePath": "box2.gltf",
                "contentType": "model/gltf+json"
            },
            "resources": [
                {
                    "relativePath": "box2.bin",
                    "contentType": "application/octet-stream"
                }
            ],
            "formatComplexity": {
                "triangleCount": "360"
            },
            "formatType": "GLTF2"
        }
    ],
    "presentationParams": {
        "orientingRotation": {
            "w": 1
        },
        "colorSpace": "LINEAR",
        "backgroundColor": "#fafafa"
    }
}