{
    "name": "snowman",
    "description": "lala",
    "authorId": "9REU1h82Qzs",
    "authorName": "sofi ka",
    "createTime": "2017-07-07T19:56:33.594796Z",
    "updateTime": "2020-10-06T09:38:53.301882Z",
    "license": "CREATIVE_COMMONS_BY",
    "visibility": "PUBLIC",
    "tags": [],
    "likes": 0,
    "formats": [
        {
            "root": {
                "relativePath": "model.gltf",
                "contentType": "model/gltf+json"
            },
            "resources": [
                {
                    "relativePath": "model.bin",
                    "contentType": "application/octet-stream"
                }
            ],
            "formatComplexity": {
                "triangleCount": "21956"
            },
            "formatType": "GLTF"
        },
        {
            "root": {
                "relativePath": "model.obj",
                "contentType": "text/plain"
            },
            "resources": [
                {
                    "relativePath": "materials.mtl",
                    "contentType": "text/plain"
                }
            ],
            "formatComplexity": {
                "triangleCount": "21956"
            },
            "formatType": "OBJ"
        },
        {
            "root": {
                "relativePath": "model.gltf",
                "contentType": "model/gltf+json"
            },
            "resources": [
                {
                    "relativePath": "model.bin",
                    "contentType": "application/octet-stream"
                }
            ],
            "formatComplexity": {
                "triangleCount": "21956"
            },
            "formatType": "GLTF2"
        }
    ],
    "presentationParams": {
        "orientingRotation": {
            "w": 1
        },
        "colorSpace": "LINEAR",
        "backgroundColor": "#9e9e9e"
    },
    "remixInfo": {
        "sourceAsset": [
            "assets/06cIVLSeOkg",
            "assets/7YGUHrkEOo8"
        ]
    }
}