{
    "name": "Do you like dragons?",
    "description": "LOVE dragons.",
    "authorId": "cQb5f2g1WBb",
    "authorName": "Erron Flaherty",
    "createTime": "2017-11-13T21:50:56.541057Z",
    "updateTime": "2020-09-24T09:45:17.864118Z",
    "license": "CREATIVE_COMMONS_BY",
    "visibility": "PUBLIC",
    "tags": [
        "tilt",
        "animals"
    ],
    "likes": 0,
    "formats": [
        {
            "root": {
                "relativePath": "Untitled_2.tilt",
                "contentType": "application/vnd-tiltbrush"
            },
            "formatComplexity": {},
            "formatType": "TILT"
        },
        {
            "root": {
                "relativePath": "tmp7b668920.gltf",
                "contentType": "model/gltf+json"
            },
            "resources": [
                {
                    "relativePath": "tmp7b668920.bin",
                    "contentType": "application/octet-stream"
                }
            ],
            "formatComplexity": {
                "triangleCount": "202384"
            },
            "formatType": "GLTF"
        }
    ],
    "presentationParams": {
        "orientingRotation": {
            "w": 1
        },
        "colorSpace": "LINEAR",
        "backgroundColor": "#000000"
    }
}