{
    "name": "026",
    "authorId": "5uxXU7kNRON",
    "authorName": "杜鵑花",
    "createTime": "2020-11-13T04:56:37.362167Z",
    "updateTime": "2020-11-13T05:04:11.287952Z",
    "license": "CREATIVE_COMMONS_BY",
    "visibility": "PUBLIC",
    "tags": [],
    "likes": 0,
    "formats": [
        {
            "root": {
                "relativePath": "model.gltf",
                "contentType": "model/gltf+json"
            },
            "resources": [
                {
                    "relativePath": "model.bin",
                    "contentType": "application/octet-stream"
                }
            ],
            "formatComplexity": {
                "triangleCount": "11388"
            },
            "formatType": "GLTF2"
        },
        {
            "root": {
                "relativePath": "Bench.fbx",
                "contentType": "application/octet-stream"
            },
            "formatComplexity": {
                "triangleCount": "11388"
            },
            "formatType": "FBX"
        }
    ],
    "presentationParams": {
        "orientingRotation": {
            "w": 1
        },
        "colorSpace": "LINEAR",
        "backgroundColor": "#fafafa"
    }
}