{
    "name": "Red Maple by José Manuel",
    "description": "Based on https://3dwarehouse.sketchup.com/model/3fcb72fcafa1479a714c06e758803700/Red-Maple-Acer-Rubrum",
    "authorId": "bsWSGscRwof",
    "authorName": "Harold Sikkema",
    "createTime": "2019-07-22T01:59:32.729819Z",
    "updateTime": "2021-01-13T10:26:44.014132Z",
    "license": "CREATIVE_COMMONS_BY",
    "visibility": "PUBLIC",
    "tags": [],
    "likes": 0,
    "formats": [
        {
            "root": {
                "relativePath": "Untitled.obj",
                "contentType": "text/plain"
            },
            "resources": [
                {
                    "relativePath": "Untitled.mtl",
                    "contentType": "text/plain"
                },
                {
                    "relativePath": "Untitled/hoja1.png",
                    "contentType": "image/png"
                },
                {
                    "relativePath": "Untitled/tl02.jpg",
                    "contentType": "image/jpeg"
                }
            ],
            "formatComplexity": {
                "triangleCount": "265089"
            },
            "formatType": "OBJ"
        },
        {
            "root": {
                "relativePath": "Untitled.gltf",
                "contentType": "model/gltf+json"
            },
            "resources": [
                {
                    "relativePath": "Untitled.bin",
                    "contentType": "application/octet-stream"
                },
                {
                    "relativePath": "Untitled/hoja1.png",
                    "contentType": "image/png"
                },
                {
                    "relativePath": "Untitled/tl02.jpg",
                    "contentType": "image/jpeg"
                }
            ],
            "formatComplexity": {
                "triangleCount": "265089"
            },
            "formatType": "GLTF2"
        }
    ],
    "presentationParams": {
        "orientingRotation": {
            "w": 1
        },
        "colorSpace": "LINEAR",
        "backgroundColor": "#eeeeee"
    }
}