{
    "name": "mousePro",
    "authorId": "97poRdPVTDV",
    "authorName": "Seb S",
    "createTime": "2020-05-27T15:37:04.992126Z",
    "updateTime": "2020-05-27T15:44:21.525529Z",
    "license": "CREATIVE_COMMONS_BY",
    "visibility": "PUBLIC",
    "tags": [],
    "likes": 0,
    "formats": [
        {
            "root": {
                "relativePath": "fil.gltf",
                "contentType": "model/gltf+json"
            },
            "resources": [
                {
                    "relativePath": "fil.bin",
                    "contentType": "application/octet-stream"
                },
                {
                    "relativePath": "fil.jpg",
                    "contentType": "image/jpeg"
                }
            ],
            "formatComplexity": {
                "triangleCount": "191897"
            },
            "formatType": "GLTF2"
        },
        {
            "root": {
                "relativePath": "fil.obj",
                "contentType": "text/plain"
            },
            "resources": [
                {
                    "relativePath": "fil.jpg",
                    "contentType": "image/jpeg"
                },
                {
                    "relativePath": "fil.mtl",
                    "contentType": "text/plain"
                }
            ],
            "formatComplexity": {
                "triangleCount": "191897"
            },
            "formatType": "OBJ"
        }
    ],
    "presentationParams": {
        "orientingRotation": {
            "x": -0.7071067811865475,
            "w": 0.7071067811865476
        },
        "colorSpace": "LINEAR",
        "backgroundColor": "#eeeeee"
    }
}