{
    "name": "vo 28",
    "authorId": "61x8MUkCOAm",
    "authorName": "nate insolitum",
    "createTime": "2020-08-23T23:03:02.950538Z",
    "updateTime": "2020-10-04T10:00:46.797938Z",
    "license": "CREATIVE_COMMONS_BY",
    "visibility": "PUBLIC",
    "tags": [],
    "likes": 0,
    "formats": [
        {
            "root": {
                "relativePath": "VO28.obj",
                "contentType": "text/plain"
            },
            "resources": [
                {
                    "relativePath": "VO28.mtl",
                    "contentType": "text/plain"
                },
                {
                    "relativePath": "1207_Birch-Mainhau-1_0001_Birch_Mainhau_diffuse3.png",
                    "contentType": "image/png"
                }
            ],
            "formatComplexity": {
                "triangleCount": "4024"
            },
            "formatType": "OBJ"
        },
        {
            "root": {
                "relativePath": "VO28.gltf",
                "contentType": "model/gltf+json"
            },
            "resources": [
                {
                    "relativePath": "VO28.bin",
                    "contentType": "application/octet-stream"
                },
                {
                    "relativePath": "1207_Birch-Mainhau-1_0001_Birch_Mainhau_diffuse3.png",
                    "contentType": "image/png"
                }
            ],
            "formatComplexity": {
                "triangleCount": "4024"
            },
            "formatType": "GLTF2"
        }
    ],
    "presentationParams": {
        "orientingRotation": {
            "w": 1
        },
        "colorSpace": "LINEAR",
        "backgroundColor": "#000000"
    }
}