{
    "name": "Bed",
    "description": "#apartment #bedroom #furniture #sleep",
    "authorId": "4aEd8rQgKu2",
    "authorName": "Poly by Google",
    "createTime": "2017-09-18T19:43:49.748042Z",
    "updateTime": "2021-06-08T06:19:43.331238Z",
    "license": "CREATIVE_COMMONS_BY",
    "visibility": "PUBLIC",
    "tags": [
        "objects",
        "curated",
        "apartment",
        "bedroom",
        "furniture",
        "sleep"
    ],
    "likes": 24,
    "formats": [
        {
            "root": {
                "relativePath": "Bed.gltf",
                "contentType": "model/gltf+json"
            },
            "resources": [
                {
                    "relativePath": "Bed.bin",
                    "contentType": "application/octet-stream"
                }
            ],
            "formatComplexity": {
                "triangleCount": "496"
            },
            "formatType": "GLTF2"
        },
        {
            "root": {
                "relativePath": "Bed.obj",
                "contentType": "text/plain"
            },
            "resources": [
                {
                    "relativePath": "Bed.mtl",
                    "contentType": "text/plain"
                }
            ],
            "formatComplexity": {
                "triangleCount": "496"
            },
            "formatType": "OBJ"
        }
    ],
    "presentationParams": {
        "orientingRotation": {
            "w": 1
        },
        "colorSpace": "LINEAR",
        "backgroundColor": "#eeeeee"
    }
}