{
    "name": "19th Century Couple Walking",
    "authorId": "axUtkrbOcRJ",
    "authorName": "Phiam Ash",
    "createTime": "2018-03-28T06:35:26.087084Z",
    "updateTime": "2020-10-02T09:41:01.903630Z",
    "license": "CREATIVE_COMMONS_BY",
    "visibility": "PUBLIC",
    "tags": [
        "people"
    ],
    "likes": 0,
    "formats": [
        {
            "root": {
                "relativePath": "walkers2g.gltf",
                "contentType": "model/gltf+json"
            },
            "resources": [
                {
                    "relativePath": "walkers2g.bin",
                    "contentType": "application/octet-stream"
                }
            ],
            "formatComplexity": {
                "triangleCount": "215652"
            },
            "formatType": "GLTF2"
        },
        {
            "root": {
                "relativePath": "walkers2g.obj",
                "contentType": "text/plain"
            },
            "resources": [
                {
                    "relativePath": "walkers2g.mtl",
                    "contentType": "text/plain"
                }
            ],
            "formatComplexity": {
                "triangleCount": "215652"
            },
            "formatType": "OBJ"
        }
    ],
    "presentationParams": {
        "orientingRotation": {
            "w": 1
        },
        "colorSpace": "LINEAR",
        "backgroundColor": "#827717"
    }
}