{
    "name": "Pineapple",
    "authorId": "6ZCYg_k59vn",
    "authorName": "Jasmine Roberts",
    "createTime": "2019-02-13T19:06:15.791488Z",
    "updateTime": "2020-10-04T10:18:30.609630Z",
    "license": "CREATIVE_COMMONS_BY",
    "visibility": "PUBLIC",
    "tags": [],
    "likes": 0,
    "formats": [
        {
            "root": {
                "relativePath": "Pineapple.gltf",
                "contentType": "model/gltf+json"
            },
            "resources": [
                {
                    "relativePath": "Pineapple.bin",
                    "contentType": "application/octet-stream"
                }
            ],
            "formatComplexity": {
                "triangleCount": "672"
            },
            "formatType": "GLTF2"
        },
        {
            "root": {
                "relativePath": "Pineapple.obj",
                "contentType": "text/plain"
            },
            "resources": [
                {
                    "relativePath": "Pineapple.mtl",
                    "contentType": "text/plain"
                }
            ],
            "formatComplexity": {
                "triangleCount": "672"
            },
            "formatType": "OBJ"
        }
    ],
    "presentationParams": {
        "orientingRotation": {
            "w": 1
        },
        "colorSpace": "LINEAR",
        "backgroundColor": "#f5f5f5"
    }
}