{
    "name": "Nuvem de Pontos do Bosque",
    "authorId": "fmY3dO-NkDp",
    "authorName": "GPUE IPPUL",
    "createTime": "2019-09-27T18:05:08.001540Z",
    "updateTime": "2020-02-25T20:27:50.810083Z",
    "license": "CREATIVE_COMMONS_BY",
    "visibility": "PUBLIC",
    "tags": [
        "architecture"
    ],
    "likes": 0,
    "formats": [
        {
            "root": {
                "relativePath": "Bosque_simplified_3d_mesh.gltf",
                "contentType": "model/gltf+json"
            },
            "resources": [
                {
                    "relativePath": "Bosque_simplified_3d_mesh.bin",
                    "contentType": "application/octet-stream"
                },
                {
                    "relativePath": "Bosque_texture.jpg",
                    "contentType": "image/jpeg"
                }
            ],
            "formatComplexity": {
                "triangleCount": "1000000"
            },
            "formatType": "GLTF2"
        },
        {
            "root": {
                "relativePath": "Bosque_simplified_3d_mesh.obj",
                "contentType": "text/plain"
            },
            "resources": [
                {
                    "relativePath": "Bosque_simplified_3d_mesh.mtl",
                    "contentType": "text/plain"
                },
                {
                    "relativePath": "Bosque_texture.jpg",
                    "contentType": "image/jpeg"
                }
            ],
            "formatComplexity": {
                "triangleCount": "1000000"
            },
            "formatType": "OBJ"
        }
    ],
    "presentationParams": {
        "orientingRotation": {
            "w": 1
        },
        "colorSpace": "LINEAR",
        "backgroundColor": "#eeeeee"
    }
}