{
    "name": "wii",
    "authorId": "fWFUV0ec6RY",
    "authorName": "Takumi",
    "createTime": "2020-10-17T02:25:04.910992Z",
    "updateTime": "2020-10-17T02:30:50.963925Z",
    "license": "CREATIVE_COMMONS_BY",
    "visibility": "PUBLIC",
    "tags": [],
    "likes": 0,
    "formats": [
        {
            "root": {
                "relativePath": "wii v6.obj",
                "contentType": "text/plain"
            },
            "formatComplexity": {
                "triangleCount": "82967"
            },
            "formatType": "OBJ"
        },
        {
            "root": {
                "relativePath": "wii v6.gltf",
                "contentType": "model/gltf+json"
            },
            "resources": [
                {
                    "relativePath": "wii v6.bin",
                    "contentType": "application/octet-stream"
                }
            ],
            "formatComplexity": {
                "triangleCount": "82967"
            },
            "formatType": "GLTF2"
        }
    ],
    "presentationParams": {
        "orientingRotation": {
            "w": 1
        },
        "colorSpace": "LINEAR",
        "backgroundColor": "#000000"
    }
}