{
    "name": "ExtCine",
    "authorId": "6m3B0r6yKt7",
    "authorName": "Luis Alonso Cardona",
    "createTime": "2020-10-30T00:14:29.297060Z",
    "updateTime": "2021-05-18T22:10:35.609463Z",
    "license": "CREATIVE_COMMONS_BY",
    "visibility": "PUBLIC",
    "tags": [],
    "likes": 0,
    "formats": [
        {
            "root": {
                "relativePath": "exteriorCine.gltf",
                "contentType": "model/gltf+json"
            },
            "resources": [
                {
                    "relativePath": "exteriorCine.bin",
                    "contentType": "application/octet-stream"
                },
                {
                    "relativePath": "CajaExterior_CajaExterior_Material_AlbedoTransparency.png",
                    "contentType": "image/png"
                },
                {
                    "relativePath": "Puerta_Puerta_Material_AlbedoTransparency.png",
                    "contentType": "image/png"
                },
                {
                    "relativePath": "Bardita1_1001_AlbedoTransparency.png",
                    "contentType": "image/png"
                },
                {
                    "relativePath": "TechoEst_TechoEst_Material_AlbedoTransparency.png",
                    "contentType": "image/png"
                },
                {
                    "relativePath": "ArcosExterior_ArcosExterior_Material_AlbedoTransparency.png",
                    "contentType": "image/png"
                },
                {
                    "relativePath": "MuroIzquierdo_MurosExterior_Material_AlbedoTransparency.png",
                    "contentType": "image/png"
                },
                {
                    "relativePath": "LetrasSustefest_LetrasSustefest_Material_AlbedoTransparency.png",
                    "contentType": "image/png"
                },
                {
                    "relativePath": "Lampara_1001_AlbedoTransparency.png",
                    "contentType": "image/png"
                },
                {
                    "relativePath": "VentPostInd_VentPostInd_Material_AlbedoTransparency.png",
                    "contentType": "image/png"
                },
                {
                    "relativePath": "ParedesFrente_ParedesFrente_Material_AlbedoTransparency.png",
                    "contentType": "image/png"
                },
                {
                    "relativePath": "ParedLetras_ParedLetras_Material_AlbedoTransparency.png",
                    "contentType": "image/png"
                },
                {
                    "relativePath": "Bardita_Bardita_Material_AlbedoTransparency.png",
                    "contentType": "image/png"
                },
                {
                    "relativePath": "Letrero_Letrero_Material_AlbedoTransparency.png",
                    "contentType": "image/png"
                },
                {
                    "relativePath": "MuroFrontal_MuroFrontal_Material_AlbedoTransparency.png",
                    "contentType": "image/png"
                },
                {
                    "relativePath": "Escape_1001_AlbedoTransparency.png",
                    "contentType": "image/png"
                },
                {
                    "relativePath": "Suelo1_Suelo1_Material_AlbedoTransparency.png",
                    "contentType": "image/png"
                },
                {
                    "relativePath": "PuertaGrande_PuertaGrande_Material_AlbedoTransparency.png",
                    "contentType": "image/png"
                },
                {
                    "relativePath": "cemento.jpg",
                    "contentType": "image/jpeg"
                },
                {
                    "relativePath": "Tejado1_Tejado_Material_AlbedoTransparency.png",
                    "contentType": "image/png"
                },
                {
                    "relativePath": "Teja_Teja_Material_AlbedoTransparency.png",
                    "contentType": "image/png"
                },
                {
                    "relativePath": "tubos_1001_AlbedoTransparency.png",
                    "contentType": "image/png"
                }
            ],
            "formatComplexity": {
                "triangleCount": "31605"
            },
            "formatType": "GLTF2"
        },
        {
            "root": {
                "relativePath": "exteriorCine.obj",
                "contentType": "text/plain"
            },
            "resources": [
                {
                    "relativePath": "exteriorCine.mtl",
                    "contentType": "text/plain"
                },
                {
                    "relativePath": "IntSuelo2_IntSuelo2_Material_Normal.png",
                    "contentType": "image/png"
                },
                {
                    "relativePath": "Lampara_1001_AlbedoTransparency.png",
                    "contentType": "image/png"
                },
                {
                    "relativePath": "Lampara_1001_Normal.png",
                    "contentType": "image/png"
                },
                {
                    "relativePath": "LetrasSustefest_LetrasSustefest_Material_AlbedoTransparency.png",
                    "contentType": "image/png"
                },
                {
                    "relativePath": "Letrero_Letrero_Material_AlbedoTransparency.png",
                    "contentType": "image/png"
                },
                {
                    "relativePath": "Letrero_Letrero_Material_Normal.png",
                    "contentType": "image/png"
                },
                {
                    "relativePath": "MuroFrontal_MuroFrontal_Material_AlbedoTransparency.png",
                    "contentType": "image/png"
                },
                {
                    "relativePath": "MuroFrontal_MuroFrontal_Material_Normal.png",
                    "contentType": "image/png"
                },
                {
                    "relativePath": "MuroIzquierdo_MurosExterior_Material_AlbedoTransparency.png",
                    "contentType": "image/png"
                },
                {
                    "relativePath": "MuroIzquierdo_MurosExterior_Material_Normal.png",
                    "contentType": "image/png"
                },
                {
                    "relativePath": "Pantalla_Pantalla_Material_AlbedoTransparency.png",
                    "contentType": "image/png"
                },
                {
                    "relativePath": "Pantalla_Pantalla_Material_Normal.png",
                    "contentType": "image/png"
                },
                {
                    "relativePath": "ParedChicaEst_ParedChicaEst_Material_AlbedoTransparency.png",
                    "contentType": "image/png"
                },
                {
                    "relativePath": "ParedChicaEst_ParedChicaEst_Material_Normal.png",
                    "contentType": "image/png"
                },
                {
                    "relativePath": "ParedesFrente_ParedesFrente_Material_AlbedoTransparency.png",
                    "contentType": "image/png"
                },
                {
                    "relativePath": "ParedesFrente_ParedesFrente_Material_Normal.png",
                    "contentType": "image/png"
                },
                {
                    "relativePath": "ParedEstaciona_Arco_Estaciona_Material_AlbedoTransparency.png",
                    "contentType": "image/png"
                },
                {
                    "relativePath": "ParedEstaciona_Arco_Estaciona_Material_Normal.png",
                    "contentType": "image/png"
                },
                {
                    "relativePath": "ParedEstaciona_ParedEstaciona_Material_AlbedoTransparency.png",
                    "contentType": "image/png"
                },
                {
                    "relativePath": "ParedEstaciona_ParedEstaciona_Material_Normal.png",
                    "contentType": "image/png"
                },
                {
                    "relativePath": "ParedLetras_ParedLetras_Material_AlbedoTransparency.png",
                    "contentType": "image/png"
                },
                {
                    "relativePath": "ParedLetras_ParedLetras_Material_Normal.png",
                    "contentType": "image/png"
                },
                {
                    "relativePath": "ParedTrasEsc_ParedTrasEsc_Material_AlbedoTransparency.png",
                    "contentType": "image/png"
                },
                {
                    "relativePath": "ParedTrasEsc_ParedTrasEsc_Material_Normal.png",
                    "contentType": "image/png"
                },
                {
                    "relativePath": "ParedTriangulo_ParedTriangulo_Material_AlbedoTransparency.png",
                    "contentType": "image/png"
                },
                {
                    "relativePath": "ParedTriangulo_ParedTriangulo_Material_Normal.png",
                    "contentType": "image/png"
                },
                {
                    "relativePath": "Puerta_Puerta_Material_AlbedoTransparency.png",
                    "contentType": "image/png"
                },
                {
                    "relativePath": "Puerta_Puerta_Material_Normal.png",
                    "contentType": "image/png"
                },
                {
                    "relativePath": "PuertaEsc_MarcoPuertaEsc_Material_AlbedoTransparency.png",
                    "contentType": "image/png"
                },
                {
                    "relativePath": "PuertaEsc_PuestaEsc_Material_AlbedoTransparency.png",
                    "contentType": "image/png"
                },
                {
                    "relativePath": "PuertaEsc_PuestaEsc_Material_Normal.png",
                    "contentType": "image/png"
                },
                {
                    "relativePath": "PuertaGrande_PuertaGrande_Material_AlbedoTransparency.png",
                    "contentType": "image/png"
                },
                {
                    "relativePath": "PuertaGrande_PuertaGrande_Material_Normal.png",
                    "contentType": "image/png"
                },
                {
                    "relativePath": "SoporteGrande_SoporteGrande_Material_AlbedoTransparency.png",
                    "contentType": "image/png"
                },
                {
                    "relativePath": "SoporteGrande_SoporteGrande_Material_Normal.png",
                    "contentType": "image/png"
                },
                {
                    "relativePath": "SoporteMediano_SoporteMediano_Material_AlbedoTransparency.png",
                    "contentType": "image/png"
                },
                {
                    "relativePath": "SoporteMediano_SoporteMediano_Material_Normal.png",
                    "contentType": "image/png"
                },
                {
                    "relativePath": "Suelo1_Suelo1_Material_AlbedoTransparency.png",
                    "contentType": "image/png"
                },
                {
                    "relativePath": "Suelo1_Suelo1_Material_Normal.png",
                    "contentType": "image/png"
                },
                {
                    "relativePath": "Taquilla_Taquilla_Material_AlbedoTransparency.png",
                    "contentType": "image/png"
                },
                {
                    "relativePath": "Taquilla_Taquilla_Material_Normal.png",
                    "contentType": "image/png"
                },
                {
                    "relativePath": "TechoEst_TechoEst_Material_AlbedoTransparency.png",
                    "contentType": "image/png"
                },
                {
                    "relativePath": "TechoEst_TechoEst_Material_Normal.png",
                    "contentType": "image/png"
                },
                {
                    "relativePath": "TechoVentanas_TechoVentanas_Material_AlbedoTransparency.png",
                    "contentType": "image/png"
                },
                {
                    "relativePath": "TechoVentanas_TechoVentanas_Material_Normal.png",
                    "contentType": "image/png"
                },
                {
                    "relativePath": "Teja_Teja_Material_AlbedoTransparency.png",
                    "contentType": "image/png"
                },
                {
                    "relativePath": "Teja_Teja_Material_Normal.png",
                    "contentType": "image/png"
                },
                {
                    "relativePath": "Tejado1_Tejado_Material_AlbedoTransparency.png",
                    "contentType": "image/png"
                },
                {
                    "relativePath": "tubos_1001_AlbedoTransparency.png",
                    "contentType": "image/png"
                },
                {
                    "relativePath": "VentPostInd_VentPostInd_Material_AlbedoTransparency.png",
                    "contentType": "image/png"
                },
                {
                    "relativePath": "VentPostInd_VentPostInd_Material_Normal.png",
                    "contentType": "image/png"
                },
                {
                    "relativePath": "Viga_1001_Normal.png",
                    "contentType": "image/png"
                },
                {
                    "relativePath": "Vitrina_Vitrina_Material_AlbedoTransparency.png",
                    "contentType": "image/png"
                },
                {
                    "relativePath": "Vitrina_Vitrina_Material_Normal.png",
                    "contentType": "image/png"
                },
                {
                    "relativePath": "ArcosExterior_ArcosExterior_Material_AlbedoTransparency.png",
                    "contentType": "image/png"
                },
                {
                    "relativePath": "ArcosExterior_ArcosExterior_Material_Normal.png",
                    "contentType": "image/png"
                },
                {
                    "relativePath": "Bardita_Bardita_Material_AlbedoTransparency.png",
                    "contentType": "image/png"
                },
                {
                    "relativePath": "Bardita_Bardita_Material_Normal.png",
                    "contentType": "image/png"
                },
                {
                    "relativePath": "Bardita1_1001_AlbedoTransparency.png",
                    "contentType": "image/png"
                },
                {
                    "relativePath": "Bardita1_1001_Normal.png",
                    "contentType": "image/png"
                },
                {
                    "relativePath": "BaseExterior_1001_AlbedoTransparency.png",
                    "contentType": "image/png"
                },
                {
                    "relativePath": "BaseExterior_1001_Normal.png",
                    "contentType": "image/png"
                },
                {
                    "relativePath": "Butaca_1001_AlbedoTransparency.png",
                    "contentType": "image/png"
                },
                {
                    "relativePath": "Butaca_1001_Normal.png",
                    "contentType": "image/png"
                },
                {
                    "relativePath": "CajaExterior_CajaExterior_Material_AlbedoTransparency.png",
                    "contentType": "image/png"
                },
                {
                    "relativePath": "CajaExterior_CajaExterior_Material_Normal.png",
                    "contentType": "image/png"
                },
                {
                    "relativePath": "cemento.jpg",
                    "contentType": "image/jpeg"
                },
                {
                    "relativePath": "ColumnaEst_ColumnaEst_Material_AlbedoTransparency.png",
                    "contentType": "image/png"
                },
                {
                    "relativePath": "ColumnaEst_ColumnaEst_Material_Normal.png",
                    "contentType": "image/png"
                },
                {
                    "relativePath": "Escalon_Escalon_Material_AlbedoTransparency.png",
                    "contentType": "image/png"
                },
                {
                    "relativePath": "Escalon_Escalon_Material_Normal.png",
                    "contentType": "image/png"
                },
                {
                    "relativePath": "Escape_1001_AlbedoTransparency.png",
                    "contentType": "image/png"
                },
                {
                    "relativePath": "Escape_1001_Normal.png",
                    "contentType": "image/png"
                }
            ],
            "formatComplexity": {
                "triangleCount": "31605"
            },
            "formatType": "OBJ"
        }
    ],
    "presentationParams": {
        "orientingRotation": {
            "w": 1
        },
        "colorSpace": "LINEAR",
        "backgroundColor": "#eeeeee"
    }
}