{
    "name": "spin it around",
    "authorId": "3pem4cRXMt6",
    "authorName": "Anthony Yu",
    "createTime": "2017-07-30T23:49:53.826273Z",
    "updateTime": "2020-10-06T09:32:07.489763Z",
    "license": "CREATIVE_COMMONS_BY",
    "visibility": "PUBLIC",
    "tags": [
        "tilt",
        "scenes",
        "curated"
    ],
    "likes": 0,
    "formats": [
        {
            "root": {
                "relativePath": "Untitled_48.tilt",
                "contentType": "application/vnd-tiltbrush"
            },
            "formatComplexity": {},
            "formatType": "TILT"
        },
        {
            "root": {
                "relativePath": "tmp6ce45876.gltf",
                "contentType": "model/gltf+json"
            },
            "resources": [
                {
                    "relativePath": "tmp6ce45876.bin",
                    "contentType": "application/octet-stream"
                }
            ],
            "formatComplexity": {
                "triangleCount": "40448"
            },
            "formatType": "GLTF"
        }
    ],
    "presentationParams": {
        "orientingRotation": {
            "w": 1
        },
        "colorSpace": "LINEAR",
        "backgroundColor": "#000000"
    }
}