{
    "name": "totc splorg circle scrongle",
    "authorId": "61x8MUkCOAm",
    "authorName": "nate insolitum",
    "createTime": "2019-10-10T00:44:32.012961Z",
    "updateTime": "2020-10-05T09:53:51.841029Z",
    "license": "CREATIVE_COMMONS_BY",
    "visibility": "PUBLIC",
    "tags": [],
    "likes": 0,
    "formats": [
        {
            "root": {
                "relativePath": "splorgcirclescrongle.gltf",
                "contentType": "model/gltf+json"
            },
            "resources": [
                {
                    "relativePath": "splorgcirclescrongle.bin",
                    "contentType": "application/octet-stream"
                }
            ],
            "formatComplexity": {
                "triangleCount": "704"
            },
            "formatType": "GLTF2"
        },
        {
            "root": {
                "relativePath": "splorgcirclescrongle.obj",
                "contentType": "text/plain"
            },
            "resources": [
                {
                    "relativePath": "splorgcirclescrongle.mtl",
                    "contentType": "text/plain"
                }
            ],
            "formatComplexity": {
                "triangleCount": "704"
            },
            "formatType": "OBJ"
        }
    ],
    "presentationParams": {
        "orientingRotation": {
            "w": 1
        },
        "colorSpace": "LINEAR",
        "backgroundColor": "#0011ff"
    }
}