{
    "name": "Blockies",
    "authorId": "bV1kmv75wbM",
    "authorName": "Darwin Yamamoto",
    "createTime": "2017-09-19T22:54:28.227239Z",
    "updateTime": "2020-10-04T10:13:39.255469Z",
    "license": "CREATIVE_COMMONS_BY",
    "visibility": "PUBLIC",
    "tags": [
        "curated"
    ],
    "likes": 10,
    "formats": [
        {
            "root": {
                "relativePath": "model.gltf",
                "contentType": "model/gltf+json"
            },
            "resources": [
                {
                    "relativePath": "model.bin",
                    "contentType": "application/octet-stream"
                }
            ],
            "formatComplexity": {
                "triangleCount": "17430"
            },
            "formatType": "GLTF2"
        },
        {
            "root": {
                "relativePath": "model.obj",
                "contentType": "text/plain"
            },
            "resources": [
                {
                    "relativePath": "materials.mtl",
                    "contentType": "text/plain"
                }
            ],
            "formatComplexity": {
                "triangleCount": "17430"
            },
            "formatType": "OBJ"
        },
        {
            "root": {
                "relativePath": "model.gltf",
                "contentType": "model/gltf+json"
            },
            "resources": [
                {
                    "relativePath": "model.bin",
                    "contentType": "application/octet-stream"
                }
            ],
            "formatComplexity": {
                "triangleCount": "17430"
            },
            "formatType": "GLTF"
        }
    ],
    "presentationParams": {
        "orientingRotation": {
            "w": 1
        },
        "colorSpace": "LINEAR",
        "backgroundColor": "#f44336"
    },
    "remixInfo": {
        "sourceAsset": [
            "assets/5R9R5RJyyAx"
        ]
    }
}