{
    "name": "Cyber Dream",
    "authorId": "aeLnKHj7ECJ",
    "authorName": "Miguelangelo Rosario",
    "createTime": "2019-09-03T08:33:03.706155Z",
    "updateTime": "2020-10-07T10:39:24.362983Z",
    "license": "CREATIVE_COMMONS_BY",
    "visibility": "PUBLIC",
    "tags": [],
    "likes": 0,
    "formats": [
        {
            "root": {
                "relativePath": "cyberdream.gltf",
                "contentType": "model/gltf+json"
            },
            "resources": [
                {
                    "relativePath": "cyberdream.bin",
                    "contentType": "application/octet-stream"
                },
                {
                    "relativePath": "cyberdream.jpg",
                    "contentType": "image/jpeg"
                }
            ],
            "formatComplexity": {
                "triangleCount": "12"
            },
            "formatType": "GLTF2"
        },
        {
            "root": {
                "relativePath": "cyberdream.obj",
                "contentType": "text/plain"
            },
            "resources": [
                {
                    "relativePath": "cyberdream.jpg",
                    "contentType": "image/jpeg"
                },
                {
                    "relativePath": "cyberdream.mtl",
                    "contentType": "text/plain"
                }
            ],
            "formatComplexity": {
                "triangleCount": "12"
            },
            "formatType": "OBJ"
        }
    ],
    "presentationParams": {
        "orientingRotation": {
            "w": 1
        },
        "colorSpace": "LINEAR",
        "backgroundColor": "#311b92"
    }
}