{
    "name": "asd",
    "authorId": "68aoGuTOes2",
    "authorName": "César Ortega",
    "createTime": "2021-05-27T04:21:52.595297Z",
    "updateTime": "2021-05-27T04:31:20.117069Z",
    "license": "CREATIVE_COMMONS_BY",
    "visibility": "PUBLIC",
    "tags": [],
    "likes": 0,
    "formats": [
        {
            "root": {
                "relativePath": "d253f0a7-f1d1-4008-ba2d-d81ec0cfaed1.obj",
                "contentType": "text/plain"
            },
            "resources": [
                {
                    "relativePath": "d253f0a7-f1d1-4008-ba2d-d81ec0cfaed1/Formica_Laminate_Dark.jpg",
                    "contentType": "image/jpeg"
                },
                {
                    "relativePath": "d253f0a7-f1d1-4008-ba2d-d81ec0cfaed1/Wood_Floor_Light.jpg",
                    "contentType": "image/jpeg"
                },
                {
                    "relativePath": "d253f0a7-f1d1-4008-ba2d-d81ec0cfaed1.mtl",
                    "contentType": "text/plain"
                }
            ],
            "formatComplexity": {
                "triangleCount": "1026"
            },
            "formatType": "OBJ"
        },
        {
            "root": {
                "relativePath": "d253f0a7-f1d1-4008-ba2d-d81ec0cfaed1.gltf",
                "contentType": "model/gltf+json"
            },
            "resources": [
                {
                    "relativePath": "d253f0a7-f1d1-4008-ba2d-d81ec0cfaed1.bin",
                    "contentType": "application/octet-stream"
                },
                {
                    "relativePath": "d253f0a7-f1d1-4008-ba2d-d81ec0cfaed1/Formica_Laminate_Dark.jpg",
                    "contentType": "image/jpeg"
                },
                {
                    "relativePath": "d253f0a7-f1d1-4008-ba2d-d81ec0cfaed1/Wood_Floor_Light.jpg",
                    "contentType": "image/jpeg"
                }
            ],
            "formatComplexity": {
                "triangleCount": "1026"
            },
            "formatType": "GLTF2"
        }
    ],
    "presentationParams": {
        "orientingRotation": {
            "w": 1
        },
        "colorSpace": "LINEAR",
        "backgroundColor": "#000000"
    }
}