{
    "name": "hex",
    "authorId": "0OF2YUD4-v6",
    "authorName": "Meshminds LASALLE",
    "createTime": "2017-11-27T07:07:54.994806Z",
    "updateTime": "2020-09-23T09:23:50.162466Z",
    "license": "CREATIVE_COMMONS_BY",
    "visibility": "PUBLIC",
    "tags": [],
    "likes": 0,
    "formats": [
        {
            "root": {
                "relativePath": "model.obj",
                "contentType": "text/plain"
            },
            "resources": [
                {
                    "relativePath": "materials.mtl",
                    "contentType": "text/plain"
                }
            ],
            "formatComplexity": {
                "triangleCount": "7356"
            },
            "formatType": "OBJ"
        },
        {
            "root": {
                "relativePath": "model.gltf",
                "contentType": "model/gltf+json"
            },
            "resources": [
                {
                    "relativePath": "model.bin",
                    "contentType": "application/octet-stream"
                }
            ],
            "formatComplexity": {
                "triangleCount": "13164"
            },
            "formatType": "GLTF"
        },
        {
            "root": {
                "relativePath": "model.fbx",
                "contentType": "application/octet-stream"
            },
            "formatComplexity": {},
            "formatType": "FBX"
        },
        {
            "root": {
                "relativePath": "model.gltf",
                "contentType": "model/gltf+json"
            },
            "resources": [
                {
                    "relativePath": "model.bin",
                    "contentType": "application/octet-stream"
                }
            ],
            "formatComplexity": {
                "triangleCount": "13164"
            },
            "formatType": "GLTF2"
        }
    ],
    "presentationParams": {
        "orientingRotation": {
            "w": 1
        },
        "colorSpace": "LINEAR",
        "backgroundColor": "#eeeeee"
    }
}