{
    "name": "3823261",
    "authorId": "b05XRC6WTe2",
    "authorName": "momo iStaging",
    "createTime": "2020-06-11T08:38:50.002326Z",
    "updateTime": "2020-07-01T09:32:02.210230Z",
    "license": "CREATIVE_COMMONS_BY",
    "visibility": "PUBLIC",
    "tags": [],
    "likes": 0,
    "formats": [
        {
            "root": {
                "relativePath": "3823261.fbx",
                "contentType": "application/octet-stream"
            },
            "formatComplexity": {
                "triangleCount": "39344"
            },
            "formatType": "FBX"
        },
        {
            "root": {
                "relativePath": "model.gltf",
                "contentType": "model/gltf+json"
            },
            "resources": [
                {
                    "relativePath": "model.bin",
                    "contentType": "application/octet-stream"
                }
            ],
            "formatComplexity": {
                "triangleCount": "39344"
            },
            "formatType": "GLTF2"
        }
    ],
    "presentationParams": {
        "orientingRotation": {
            "w": 1
        },
        "colorSpace": "LINEAR",
        "backgroundColor": "#fafafa"
    }
}